CHANGES.txt
COPYRIGHT.txt
LICENSE.txt
README.txt
setup.py
src/stxnext/__init__.py
src/stxnext.pdb.egg-info/PKG-INFO
src/stxnext.pdb.egg-info/SOURCES.txt
src/stxnext.pdb.egg-info/dependency_links.txt
src/stxnext.pdb.egg-info/namespace_packages.txt
src/stxnext.pdb.egg-info/not-zip-safe
src/stxnext.pdb.egg-info/requires.txt
src/stxnext.pdb.egg-info/top_level.txt
src/stxnext/pdb/__init__.py
src/stxnext/pdb/browser.py
src/stxnext/pdb/configure.zcml
src/stxnext/pdb/debugger.py
src/stxnext/pdb/stxnext.pdb-configure.zcml
src/stxnext/pdb/zodbanalyze.py