Metadata-Version: 1.0
Name: stxnext.pdb
Version: 0.2.0
Summary: This is extended Python Debugger (pdb). It offers few very useful features that helps in debugging, especially zope2/zope3/plone instances.
Home-page: http://stxnext.pl/open-source/stxnext.pdb
Author: STX Next Sp. z o.o, Wojciech Lichota
Author-email: info@stxnext.pl, wojciech.lichota@stxnext.pl
License: Zope Public License, Version 2.1 (ZPL)
Keywords: python debug debugger pdb
Platform: any
Classifier: Development Status :: 3 - Alpha
Classifier: Framework :: Zope2
Classifier: Framework :: Zope3
Classifier: Framework :: Plone
Classifier: Environment :: Console
Classifier: Intended Audience :: Developers
Classifier: License :: OSI Approved :: Zope Public License
Classifier: Natural Language :: English
Classifier: Programming Language :: Python
Classifier: Topic :: Software Development :: Debuggers
Classifier: Topic :: Software Development :: Libraries :: Python Modules
